zerorunner_consul/__init__.py
zerorunner_consul/aio.py
zerorunner_consul/cb.py
zerorunner_consul/check.py
zerorunner_consul/consul.py
zerorunner_consul/exception.py
zerorunner_consul/http_client.py
zerorunner_consul/std.py
zerorunner_consul-0.2.1.dist-info/METADATA
zerorunner_consul-0.2.1.dist-info/WHEEL
zerorunner_consul-0.2.1.dist-info/RECORD
